quesadilla/meta.py
quesadilla/py.typed
quesadilla-0.5.0.post1.dist-info/LICENSE
quesadilla-0.5.0.post1.dist-info/METADATA
quesadilla-0.5.0.post1.dist-info/WHEEL
quesadilla-0.5.0.post1.dist-info/RECORD
